cv_preprocess.py
cv_preprocess-0.1.0.dist-info/licenses/LICENSE
cv_preprocess-0.1.0.dist-info/METADATA
cv_preprocess-0.1.0.dist-info/WHEEL
cv_preprocess-0.1.0.dist-info/top_level.txt
cv_preprocess-0.1.0.dist-info/RECORD
